{
  "id": "gentle-touch",
  "name": "AFOD.Playbooks.gentle-touch",
  "description": "AFOD.Playbooks.gentle-touchDescription",
  "modules": {
    "ratings": {
      "startingRatings": {
        "read": 2,
        "consort": 1
      }
    },
    "items": {
      "custom": [
        {
          "id": "fine concealed palm pistol",
          "name": "AFOD.Modules.itemsFineConcealedPalmPistol",
          "load": 1
        },
        {
          "id": "fine bedside manners",
          "name": "AFOD.Modules.itemsFineBedsideManners",
          "load": 0
        },
        {
          "id": "fine doctors bag and apron",
          "name": "AFOD.Modules.itemsFineDoctorsBagAndApron",
          "load": 2
        },
        {
          "id": "fine and very strong cough syrup",
          "name": "AFOD.Modules.itemsFineAndVeryStrongCoughSyrup",
          "load": 0
        },
        {
          "id": "a comforting song",
          "name": "AFOD.Modules.itemsAComfortingSong",
          "load": 0
        },
        {
          "id": "an old favor",
          "name": "AFOD.Modules.itemsAnOldFavor",
          "load": 0
        }
      ]
    },
    "specialAbilities": {
      "abilities": [
        {
          "id": "snake oil miracles",
          "name": "AFOD.Modules.specialAbilitiesSnakeOilMiracles",
          "description": "AFOD.Modules.specialAbilitiesSnakeOilMiraclesDescription"
        },
        {
          "id": "influential",
          "name": "AFOD.Modules.specialAbilitiesInfluential",
          "description": "AFOD.Modules.specialAbilitiesInfluentialDescription"
        },
        {
          "id": "little vultures",
          "name": "AFOD.Modules.specialAbilitiesLittleVultures",
          "description": "AFOD.Modules.specialAbilitiesLittleVulturesDescription"
        },
        {
          "id": "well travelled",
          "name": "AFOD.Modules.specialAbilitiesWellTravelled",
          "description": "AFOD.Modules.specialAbilitiesWellTravelledDescription"
        },
        {
          "id": "fandango",
          "name": "AFOD.Modules.specialAbilitiesFandango",
          "description": "AFOD.Modules.specialAbilitiesFandangoDescription"
        },
        {
          "id": "quick-witted",
          "name": "AFOD.Modules.specialAbilitiesQuickWitted",
          "description": "AFOD.Modules.specialAbilitiesQuickWittedDescription"
        },
        {
          "id": "viper",
          "name": "AFOD.Modules.specialAbilitiesViper",
          "description": "AFOD.Modules.specialAbilitiesViperDescription"
        },
        {
          "id": "in good hands",
          "name": "AFOD.Modules.specialAbilitiesInGoodHands",
          "description": "AFOD.Modules.specialAbilitiesInGoodHandsDescription"
        },
        {
          "id": "veteran",
          "name": "AFOD.Modules.specialAbilitiesVeteran",
          "max": 3,
          "description": "AFOD.Modules.specialAbilitiesVeteranDescription"
        }
      ]
    },
    "contacts": {
      "contacts": [
        {
          "id": "mitch cochran",
          "name": "AFOD.Modules.contactsMitchCochran"
        },
        {
          "id": "janet irsinghausen",
          "name": "AFOD.Modules.contactsJanetIrsinghausen"
        },
        {
          "id": "mr rosenberg",
          "name": "AFOD.Modules.contactsMrRosenberg"
        },
        {
          "id": "joe sawyer",
          "name": "AFOD.Modules.contactsJoeSawyer"
        },
        {
          "id": "ron maddox",
          "name": "AFOD.Modules.contactsRonMaddox"
        }
      ]
    }
  }
}