{
  "id": "thunderheart",
  "name": "AFOD.Playbooks.thunderheart",
  "description": "AFOD.Playbooks.thunderheartDescription",
  "modules": {
    "ratings": {
      "startingRatings": {
        "survey": 1,
        "prowl": 1,
        "attune": 1
      }
    },
    "items": {
      "custom": [
        {
          "id": "fine bow with arrows",
          "name": "AFOD.Modules.itemsFinebowWithArrows",
          "load": 1
        },
        {
          "id": "fine weapon",
          "name": "AFOD.Modules.itemsFineWeapon",
          "load": 1
        },
        {
          "id": "a spirit bane or charm",
          "name": "AFOD.Modules.itemsASpiritBaneOrCharm",
          "load": 0
        },
        {
          "id": "outdoor survival kit",
          "name": "AFOD.Modules.itemsOutdoorSurvivalKit",
          "load": 1
        },
        {
          "id": "tabaco poison medicine",
          "name": "AFOD.Modules.itemsTabacoPoisonMedicine",
          "load": 1
        },
        {
          "id": "a totem's gift",
          "name": "AFOD.Modules.itemsATotemsGift",
          "load": 1
        }
      ]
    },
    "specialAbilities": {
      "abilities": [
        {
          "id": "guided by the totem",
          "name": "AFOD.Modules.specialAbilitiesGuidedByTheTotem",
          "description": "AFOD.Modules.specialAbilitiesGuidedByTheTotemDescription"
        },
        {
          "id": "totem's vessel",
          "name": "AFOD.Modules.specialAbilitiesTotemsVessel",
          "description": "AFOD.Modules.specialAbilitiesTotemsVesselDescription"
        },
        {
          "id": "protector of the people",
          "name": "AFOD.Modules.specialAbilitiesProtectorOfThePeople",
          "description": "AFOD.Modules.specialAbilitiesProtectorOfThePeopleDescription"
        },
        {
          "id": "a devil with a blade",
          "name": "AFOD.Modules.specialAbilitiesADevilWithABlade",
          "description": "AFOD.Modules.specialAbilitiesADevilWithABladeDescription"
        },
        {
          "id": "gruesome warpaint",
          "name": "AFOD.Modules.specialAbilitiesGruesomeWarpaint",
          "description": "AFOD.Modules.specialAbilitiesGruesomeWarpaintDescription"
        },
        {
          "id": "totem sense",
          "name": "AFOD.Modules.specialAbilitiesTotemSense",
          "description": "AFOD.Modules.specialAbilitiesTotemSenseDescription"
        },
        {
          "id": "lone wolf",
          "name": "AFOD.Modules.specialAbilitiesLoneWolf",
          "description": "AFOD.Modules.specialAbilitiesLoneWolfDescription"
        },
        {
          "id": "veteran",
          "name": "AFOD.Modules.specialAbilitiesVeteranCharacter",
          "max": 3,
          "description": "AFOD.Modules.specialAbilitiesVeteranCharacterDescription"
        }
      ]
    },
    "contacts": {
      "contacts": [
        {
          "id": "the petrified tree",
          "name": "AFOD.Modules.contactsThePetrifiedTree"
        },
        {
          "id": "maxwell",
          "name": "AFOD.Modules.contactsMaxwell"
        },
        {
          "id": "black hoof",
          "name": "AFOD.Modules.contactsBlackHoof"
        },
        {
          "id": "red horse",
          "name": "AFOD.Modules.contactsRedHorse"
        },
        {
          "id": "hunter",
          "name": "AFOD.Modules.contactsHunter"
        }
      ]
    }
  }
}
